googlegallary/__init__.py
googlegallary-0.5.0.dist-info/METADATA
googlegallary-0.5.0.dist-info/WHEEL
googlegallary-0.5.0.dist-info/top_level.txt
googlegallary-0.5.0.dist-info/RECORD
