Metadata-Version: 2.1
Name: googlegallary
Version: 0.5.0
Summary: Your can get images by using this package 
Author: Rahul chauhan
